sapphirecms/cli/__init__.py
sapphirecms/html/__init__.py
sapphirecms/logs/__init__.py
sapphirecms/networking/__init__.py
sapphirecms/networking/request.py
sapphirecms/networking/response.py
sapphirecms/routing/__init__.py
sapphirecms/security/__init__.py
sapphirecms/storage/__init__.py
sapphirecms/storage/adapter/MongoDB.py
sapphirecms/storage/adapter/__init__.py
sapphirecms/storage/models/__init__.py
sapphirecms-0.0.0a0.dist-info/LICENSE
sapphirecms-0.0.0a0.dist-info/METADATA
sapphirecms-0.0.0a0.dist-info/WHEEL
sapphirecms-0.0.0a0.dist-info/entry_points.txt
sapphirecms-0.0.0a0.dist-info/top_level.txt
sapphirecms-0.0.0a0.dist-info/RECORD
