Metadata-Version: 2.1
Name: sapphirecms
Version: 0.0.0a0
Summary: SapphireCMS is a modern, open-source, and easy-to-use Content Management System (CMS) for building websites. SapphireCMS is built on top of Python and is designed to be simple, flexible, and extensible.
Author-email: Sushant Shah <mail@sushantshah.dev>
Maintainer-email: Sushant Shah <mail@sushantshah.dev>
License: MIT License
Project-URL: Homepage, https://sapphirecms.github.io/
Project-URL: Documentation, https://sapphirecms.github.io/docs/
Project-URL: Repository, https://github.com/SapphireCMS/SapphireCMS
Requires-Python: >=3.11
License-File: LICENSE
Requires-Dist: pyjwt
Requires-Dist: pymongo
Requires-Dist: requests
